{
    "status": "success",
    "thing_content": "**Event Analysis:**\n\nE001\nDate: (Not specified)\nTitle: Welcome and Music\nTime: 8:30 - 8:50\nDuration: 20 minutes\nHost: (Not specified)\nLocation: (Not specified)\nCategories: Welcome, Music, Spiritual Gathering\nDescription: Welcome and introductory music for the one-day event.\n\nE002\nDate: (Not specified)\nTitle: Session 1: Finding Purpose in Your Life\nTime: 8:50 - 9:40\nDuration: 50 minutes\nHost: (Not specified)\nLocation: (Not specified)\nCategories: Spiritual Guidance, Personal Development, Life Purpose\nDescription: A session focused on finding purpose in one's life.\n\nE003\nDate: (Not specified)\nTitle: Small Group Discussion #1\nTime: 9:40 - 10:00\nDuration: 20 minutes\nHost: (Not specified)\nLocation: (Not specified)\nCategories: Group Discussion, Spiritual Growth, Community Building\nDescription: A small group discussion following Session 1.\n\nE004\nDate: (Not specified)\nTitle: Session 2: Finding Respect and Honor at Home\nTime: 10:10 - 11:00\nDuration: 50 minutes\nHost: (Not specified)\nLocation: (Not specified)\nCategories: Family Relationships, Respect, Honor\nDescription: A session focused on finding respect and honor at home.\n\nE005\nDate: (Not specified)\nTitle: Small Group Discussion #2\nTime: 11:00 - 11:20\nDuration: 20 minutes\nHost: (Not specified)\nLocation: (Not specified)\nCategories: Group Discussion, Family Dynamics, Personal Growth\nDescription: A small group discussion following Session 2.\n\nE006\nDate: (Not specified)\nTitle: Gather/Pray\nTime: 11:20 - 11:25\nDuration: 5 minutes\nHost: (Not specified)\nLocation: (Not specified)\nCategories: Prayer, Spiritual Reflection\nDescription: A brief gathering for prayer.\n\nE007\nDate: (Not specified)\nTitle: Lunch / Faculty meets with Follow-Up Group Leaders\nTime: 11:25 - 12:15\nDuration: 50 minutes\nHost: (Not specified)\nLocation: (Not specified)\nCategories: Networking, Community Building, Leadership\nDescription: A lunch break with faculty meeting with follow-up group leaders.\n\nE008\nDate: (Not specified)\nTitle: Gather/Music (one song)\nTime: 12:15 - 12:30\nDuration: 15 minutes\nHost: (Not specified)\nLocation: (Not specified)\nCategories: Music, Spiritual Gathering\nDescription: A brief gathering with music.\n\nE009\nDate: (Not specified)\nTitle: Session 3: Finding a New Best Friend in Your Wife\nTime: 12:30 - 1:20\nDuration: 50 minutes\nHost: (Not specified)\nLocation: (Not specified)\nCategories: Marriage, Relationships, Personal Growth\nDescription: A session focused on finding a new best friend in one's wife.\n\nE010\nDate: (Not specified)\nTitle: Formation of six-week follow-up groups and discussion #3\nTime: 1:20 - 2:00\nDuration: 40 minutes\nHost: (Not specified)\nLocation: (Not specified)\nCategories: Community Building, Group Discussion, Personal Growth\nDescription: Formation of six-week follow-up groups and a group discussion.\n\nE011\nDate: (Not specified)\nTitle: Session 4: Finding a Deeper Relationship with God\nTime: 2:00 - 2:50\nDuration: 50 minutes\nHost: (Not specified)\nLocation: (Not specified)\nCategories: Spiritual Growth, Personal Development, Faith\nDescription: A session focused on finding a deeper relationship with God.\n\nE012\nDate: (Not specified)\nTitle: Small Group Discussion #4\nTime: 2:50 - 3:10\nDuration: 20 minutes\nHost: (Not specified)\nLocation: (Not specified)\nCategories: Group Discussion, Spiritual Reflection, Community Building\nDescription: A small group discussion following Session 4.\n\nE013\nDate: (Not specified)\nTitle: Wrap-Up/Music/Close\nTime: 3:10 - 3:20\nDuration: 10 minutes\nHost: (Not specified)\nLocation: (Not specified)\nCategories: Closing, Music, Spiritual Gathering\nDescription: A brief closing with music.\n\n**Overall Itinerary Analysis:**\n\nThe one-day event appears to be a spiritual gathering focused on personal growth, relationships, and spiritual development. Key themes include:\n\n1. Spiritual Growth: Exploring one's relationship with God and finding purpose in life.\n2. Relationships: Focusing on respect and honor at home, and building a deeper connection with one's wife.\n3. Community Building: Encouraging group discussions, networking, and community building.\n\nThe target audience seems to be individuals seeking spiritual growth and personal development, particularly men. The event combines various formats, including sessions, small group discussions, music, and prayer, to provide a comprehensive and engaging experience.\n\nThe general focus is on providing a supportive environment for attendees to explore their spiritual lives, build meaningful relationships, and find purpose and direction.",
    "json_thing_content": {
        "events": [
            {
                "event_id": "E001",
                "date": "",
                "title": "Welcome and Music",
                "start_time": "8:30",
                "end_time": "8:50",
                "duration": 20,
                "host": [],
                "location": "",
                "categories": [
                    "Welcome",
                    "Music",
                    "Spiritual Gathering"
                ],
                "description": "Welcome and introductory music for the one-day event."
            },
            {
                "event_id": "E002",
                "date": "",
                "title": "Session 1: Finding Purpose in Your Life",
                "start_time": "8:50",
                "end_time": "9:40",
                "duration": 50,
                "host": [],
                "location": "",
                "categories": [
                    "Spiritual Guidance",
                    "Personal Development",
                    "Life Purpose"
                ],
                "description": "A session focused on finding purpose in one's life."
            },
            {
                "event_id": "E003",
                "date": "",
                "title": "Small Group Discussion #1",
                "start_time": "9:40",
                "end_time": "10:00",
                "duration": 20,
                "host": [],
                "location": "",
                "categories": [
                    "Group Discussion",
                    "Spiritual Growth",
                    "Community Building"
                ],
                "description": "A small group discussion following Session 1."
            },
            {
                "event_id": "E004",
                "date": "",
                "title": "Session 2: Finding Respect and Honor at Home",
                "start_time": "10:10",
                "end_time": "11:00",
                "duration": 50,
                "host": [],
                "location": "",
                "categories": [
                    "Family Relationships",
                    "Respect",
                    "Honor"
                ],
                "description": "A session focused on finding respect and honor at home."
            },
            {
                "event_id": "E005",
                "date": "",
                "title": "Small Group Discussion #2",
                "start_time": "11:00",
                "end_time": "11:20",
                "duration": 20,
                "host": [],
                "location": "",
                "categories": [
                    "Group Discussion",
                    "Family Dynamics",
                    "Personal Growth"
                ],
                "description": "A small group discussion following Session 2."
            },
            {
                "event_id": "E006",
                "date": "",
                "title": "Gather/Pray",
                "start_time": "11:20",
                "end_time": "11:25",
                "duration": 5,
                "host": [],
                "location": "",
                "categories": [
                    "Prayer",
                    "Spiritual Reflection"
                ],
                "description": "A brief gathering for prayer."
            },
            {
                "event_id": "E007",
                "date": "",
                "title": "Lunch / Faculty meets with Follow-Up Group Leaders",
                "start_time": "11:25",
                "end_time": "12:15",
                "duration": 50,
                "host": [],
                "location": "",
                "categories": [
                    "Networking",
                    "Community Building",
                    "Leadership"
                ],
                "description": "A lunch break with faculty meeting with follow-up group leaders."
            },
            {
                "event_id": "E008",
                "date": "",
                "title": "Gather/Music (one song)",
                "start_time": "12:15",
                "end_time": "12:30",
                "duration": 15,
                "host": [],
                "location": "",
                "categories": [
                    "Music",
                    "Spiritual Gathering"
                ],
                "description": "A brief gathering with music."
            },
            {
                "event_id": "E009",
                "date": "",
                "title": "Session 3: Finding a New Best Friend in Your Wife",
                "start_time": "12:30",
                "end_time": "1:20",
                "duration": 50,
                "host": [],
                "location": "",
                "categories": [
                    "Marriage",
                    "Relationships",
                    "Personal Growth"
                ],
                "description": "A session focused on finding a new best friend in one's wife."
            },
            {
                "event_id": "E010",
                "date": "",
                "title": "Formation of six-week follow-up groups and discussion #3",
                "start_time": "1:20",
                "end_time": "2:00",
                "duration": 40,
                "host": [],
                "location": "",
                "categories": [
                    "Community Building",
                    "Group Discussion",
                    "Personal Growth"
                ],
                "description": "Formation of six-week follow-up groups and a group discussion."
            },
            {
                "event_id": "E011",
                "date": "",
                "title": "Session 4: Finding a Deeper Relationship with God",
                "start_time": "2:00",
                "end_time": "2:50",
                "duration": 50,
                "host": [],
                "location": "",
                "categories": [
                    "Spiritual Growth",
                    "Personal Development",
                    "Faith"
                ],
                "description": "A session focused on finding a deeper relationship with God."
            },
            {
                "event_id": "E012",
                "date": "",
                "title": "Small Group Discussion #4",
                "start_time": "2:50",
                "end_time": "3:10",
                "duration": 20,
                "host": [],
                "location": "",
                "categories": [
                    "Group Discussion",
                    "Spiritual Reflection",
                    "Community Building"
                ],
                "description": "A small group discussion following Session 4."
            },
            {
                "event_id": "E013",
                "date": "",
                "title": "Wrap-Up/Music/Close",
                "start_time": "3:10",
                "end_time": "3:20",
                "duration": 10,
                "host": [],
                "location": "",
                "categories": [
                    "Closing",
                    "Music",
                    "Spiritual Gathering"
                ],
                "description": "A brief closing with music."
            }
        ]
    }
}